{
    "title": "My Awesome Embed",
    "description": "This is a description of the embed.",
    "url": "https://your-site.pages.dev",
    "color": 15258703,
    "author": {
      "name": "Author Name",
      "url": "https://your-site.pages.dev",
      "icon_url": "https://your-site.pages.dev/author-icon.png"
    },
    "provider": {
      "name": "Provider Name",
      "url": "https://your-site.pages.dev"
    },
    "image": {
      "url": "https://your-site.pages.dev/image.png"
    },
    "video": {
      "url": "https://your-site.pages.dev/video.mp4"
    },
    "thumbnail": {
      "url": "https://your-site.pages.dev/thumbnail.png"
    }
  }